pyflagsercount/__init__.py
pyflagsercount/flagser_count_bindings.cpp
pyflagsercount/flagser_functions.py
pyflagsercount/include/argparser.h
pyflagsercount/include/cnpy.h
pyflagsercount/include/definitions.h
pyflagsercount/include/directed_flag_complex.h
pyflagsercount/include/directed_graph.h
pyflagsercount/include/input.h
pyflagsercount/modules/flagsercount_pybind.cpython-38-x86_64-linux-gnu.so
pyflagsercount/pybind11/.appveyor.yml
pyflagsercount/pybind11/.clang-format
pyflagsercount/pybind11/.clang-tidy
pyflagsercount/pybind11/.cmake-format.yaml
pyflagsercount/pybind11/.codespell-ignore-lines
pyflagsercount/pybind11/.git/HEAD
pyflagsercount/pybind11/.git/config
pyflagsercount/pybind11/.git/description
pyflagsercount/pybind11/.git/hooks/applypatch-msg.sample
pyflagsercount/pybind11/.git/hooks/commit-msg.sample
pyflagsercount/pybind11/.git/hooks/fsmonitor-watchman.sample
pyflagsercount/pybind11/.git/hooks/post-update.sample
pyflagsercount/pybind11/.git/hooks/pre-applypatch.sample
pyflagsercount/pybind11/.git/hooks/pre-commit.sample
pyflagsercount/pybind11/.git/hooks/pre-merge-commit.sample
pyflagsercount/pybind11/.git/hooks/pre-push.sample
pyflagsercount/pybind11/.git/hooks/pre-rebase.sample
pyflagsercount/pybind11/.git/hooks/pre-receive.sample
pyflagsercount/pybind11/.git/hooks/prepare-commit-msg.sample
pyflagsercount/pybind11/.git/hooks/update.sample
pyflagsercount/pybind11/.git/index
pyflagsercount/pybind11/.git/info/exclude
pyflagsercount/pybind11/.git/logs/HEAD
pyflagsercount/pybind11/.git/logs/refs/heads/master
pyflagsercount/pybind11/.git/logs/refs/remotes/origin/HEAD
pyflagsercount/pybind11/.git/objects/pack/pack-a0cf4aba3f1b237dd4dece221f429325e0949161.idx
pyflagsercount/pybind11/.git/objects/pack/pack-a0cf4aba3f1b237dd4dece221f429325e0949161.pack
pyflagsercount/pybind11/.git/packed-refs
pyflagsercount/pybind11/.git/refs/heads/master
pyflagsercount/pybind11/.git/refs/remotes/origin/HEAD
pyflagsercount/pybind11/.gitattributes
pyflagsercount-0.2.30.dist-info/WHEEL
pyflagsercount-0.2.30.dist-info/METADATA
pyflagsercount-0.2.30.dist-info/RECORD
