Metadata-Version: 2.1
Name: pyflagsercount
Version: 0.2.30
Summary: A program for counting directed cliques in directed graphs
License: GNU AGPLv3
Author: jasonpsmith
Author-email: jasonsmith.bath@gmail.com
Requires-Python: >=3.7,<4.0
Classifier: License :: Other/Proprietary License
Classifier: Programming Language :: Python :: 3
Classifier: Programming Language :: Python :: 3.7
Classifier: Programming Language :: Python :: 3.8
Classifier: Programming Language :: Python :: 3.9
Classifier: Programming Language :: Python :: 3.10
Classifier: Programming Language :: Python :: 3.11
Requires-Dist: numpy (>=1.17.0)
Requires-Dist: pybind11 (>=2.8.0,<3.0.0)
